pdf_wrapper/__init__.py
pdf_wrapper/pdf_wrapper.py
pdf_wrapper-0.1.0.dist-info/METADATA
pdf_wrapper-0.1.0.dist-info/WHEEL
pdf_wrapper-0.1.0.dist-info/top_level.txt
pdf_wrapper-0.1.0.dist-info/RECORD
